multiupload_plus/__init__.py
multiupload_plus/fields.py
multiupload_plus/tests/__init__.py
multiupload_plus/tests/test_field.py
multiupload_plus/tests/test_input.py
multiupload_plus/tests/utils.py
django_multiupload_plus-0.1.0.dist-info/AUTHORS
django_multiupload_plus-0.1.0.dist-info/LICENSE
django_multiupload_plus-0.1.0.dist-info/METADATA
django_multiupload_plus-0.1.0.dist-info/WHEEL
django_multiupload_plus-0.1.0.dist-info/top_level.txt
django_multiupload_plus-0.1.0.dist-info/RECORD
